{
  "streams": [
    {
      "title": "new streams edited",
      "description": "edited",
      "userId": "108609871328401069478",
      "id": 1
    },
    {
      "title": "new",
      "description": "new one",
      "userId": "108609871328401069478",
      "id": 2
    },
    {
      "title": "new",
      "description": "did it",
      "userId": "108609871328401069478",
      "id": 3
    },
    {
      "title": "new",
      "description": "made with history",
      "userId": "108609871328401069478",
      "id": 4
    },
    {
      "title": "new ",
      "description": "made with history ",
      "userId": "108609871328401069478",
      "id": 5
    },
    {
      "title": "new",
      "description": "new made",
      "userId": "108609871328401069478",
      "id": 6
    },
    {
      "title": "asd",
      "description": "asd",
      "userId": "108609871328401069478",
      "id": 7
    },
    {
      "title": "asd",
      "description": "asd",
      "userId": "108609871328401069478",
      "id": 8
    },
    {
      "userId": "108609871328401069478",
      "id": 9
    },
    {
      "userId": "108609871328401069478",
      "id": 10
    },
    {
      "title": "asd",
      "description": "asd",
      "userId": "108609871328401069478",
      "id": 11
    },
    {
      "title": "asd",
      "description": "asd",
      "userId": "108609871328401069478",
      "id": 12
    }
  ]
}